Automation3270TK4/__init__.py
Automation3270TK4-0.1.3.dist-info/LICENSE
Automation3270TK4-0.1.3.dist-info/METADATA
Automation3270TK4-0.1.3.dist-info/WHEEL
Automation3270TK4-0.1.3.dist-info/top_level.txt
Automation3270TK4-0.1.3.dist-info/RECORD
